{"singlePage": [], "startSite": "", "filingNum": "", "onePageListNum": 15, "commentLabelColor": "#006b75", "yearColorList": ["#bc4c00", "#0969da", "#1f883d", "#A333D0"], "i18n": "CN", "themeMode": "manual", "dayTheme": "light", "nightTheme": "dark", "urlMode": "pinyin", "script": "", "style": "", "head": "", "indexScript": "", "indexStyle": "", "bottomText": "", "showPostSource": 1, "iconList": {}, "UTC": 8, "rssSplit": "sentence", "exlink": {}, "needComment": 1, "allHead": "", "title": "Absoluter Geist", "subTitle": "\u7eb5\u4f7f\u65f6\u5149\u4e07\u5e74\u9065\uff0c\u5c06\u611f\u6211\u5fc3\u5728\u54ab\u5c3a\u3002", "avatarUrl": "https://avatars.githubusercontent.com/u/101440642?s=400&u=06c88f077afc7b58938225692af72f3644e8b1ba&v=4", "GMEEK_VERSION": "last", "postListJson": {"P1": {"htmlDir": "docs/post/Hellow world!.html", "labels": ["documentation"], "postTitle": "Hellow world!", "postUrl": "post/Hellow%20world%21.html", "postSourceUrl": "https://github.com/wangjiawenmath/das-sein.github.io/issues/1", "commentNum": 0, "wordCount": 43, "description": "\r\n![Uploading \u5fae\u4fe1\u56fe\u7247_20240927112606.jpg\u2026]()\r\n\u3002", "top": 0, "createdAt": 1731503962, "style": "", "script": "", "head": "", "ogImage": "https://avatars.githubusercontent.com/u/101440642?s=400&u=06c88f077afc7b58938225692af72f3644e8b1ba&v=4", "createdDate": "2024-11-13", "dateLabelColor": "#bc4c00"}}, "singeListJson": {}, "labelColorDict": {"bug": "#d73a4a", "documentation": "#0075ca", "duplicate": "#cfd3d7", "enhancement": "#a2eeef", "good first issue": "#7057ff", "help wanted": "#008672", "invalid": "#e4e669", "question": "#d876e3", "wontfix": "#ffffff"}, "displayTitle": "Absoluter Geist", "faviconUrl": "https://avatars.githubusercontent.com/u/101440642?s=400&u=06c88f077afc7b58938225692af72f3644e8b1ba&v=4", "ogImage": "https://avatars.githubusercontent.com/u/101440642?s=400&u=06c88f077afc7b58938225692af72f3644e8b1ba&v=4", "primerCSS": "<link href='https://mirrors.sustech.edu.cn/cdnjs/ajax/libs/Primer/21.0.7/primer.css' rel='stylesheet' />", "homeUrl": "https://wangjiawenmath.github.io/das-sein.github.io", "prevUrl": "disabled", "nextUrl": "disabled"}